Workbook

Sheet Aannames
B2: Aannames

Sheet MarketCap
B2: MSCI ACWI IMI | C2: 53732257 | F2: Kosten | I2: lek
F3: World | G3: =C5/C11 -> 0.78772395 | H3: =$G$16*G3 -> 0.00094526874 | I3: =G3*DividendLek!I11 -> 0.14400185 | K3: World | L3: =C5/C12 -> 0.87840423 | M3: =L3*DividendLek!I11 -> 0.16057888
F4: Small | G4: =C6/C11 -> 0.10323297 | H4: =$G$17*G4 -> 0.00032002222 | I4: =G4*DividendLek!I17 -> 0.019233078 | K4: Emerging | L4: =C7/C12 -> 0.12159577 | M4: =L4*DividendLek!I23 -> 0.012817509
B5: MSCI World | C5: 41819773 | D5: =C5/$C$2 -> 0.7782992 | F5: EM | G5: =C7/C11 -> 0.10904307 | H5: =$G$18*G5 -> 0.00020718184 | I5: =G5*DividendLek!I23 -> 0.01149432 | M5: =SUM(M3:M4) -> 0.17339639
B6: MSCI World SC | C6: 5480574.1 | D6: =C6/$C$2 -> 0.10199784 | H6: =SUM(H3:H5) -> 0.0014724728 | I6: =SUM(I3:I5) -> 0.17472924
B7: MSCI Emerging | C7: 5789028.7 | D7: =C7/$C$2 -> 0.10773842
B8: EM small caps | C8: 642881.35 | D8: =C8/$C$2 -> 0.011964533 | F8: Dividend lek
B9: cross check | C9: =SUM(C5:C8) -> 53732257 | F9: Totaal
B11: MSCI ACWI IMI - EM Small | C11: =C2-C8 -> 53089376
B12: World + Emerging | C12: =C5+C7 -> 47608802
B14: Kosten uit https://global.vanguard.com/portal/site/loadPDF?country=global&docId=15835
B16: Vanguard Global Stock Index Fund Institutional Plus EUR Acc | G16: 0.0012
B17: Vanguard Global Small-Cap Index Fund Institutional Plus EUR Acc | G17: =0.24%+0.02%+0.05% -> 0.0031
B18: Vanguard Emerging Markets Stock Index Fund Institutional Plus EUR Acc | G18: =0.16%+0.01%+0.02% -> 0.0019
B20: Vanguard FTSE All-World | G20: =0.22%+0.02% -> 0.0024
B21: Dividend lek bij 2,5% | G21: =DividendLek!I5*2.5% -> 0.0028556187
B22: Totaal | G22: =SUM(G20:G21) -> 0.0052556187
B24: Fondsen | G24: =H6 -> 0.0014724728
B25: Dividend lek bij 2,5% | G25: =M5*2.5% -> 0.0043349098
B26: Totaal | G26: =SUM(G24:G25) -> 0.0058073826
B29: Vanguard FTSE All-World | G29: =0.22%+0.02% -> 0.0024
B30: Dividend lek bij 2% | G30: =DividendLek!I5*2% -> 0.002284495
B31: Totaal | G31: =SUM(G29:G30) -> 0.004684495
B33: Fondsen | G33: =H6 -> 0.0014724728
B34: Dividend lek bij 2% | G34: =M5*2% -> 0.0034679278
B35: Totaal | G35: =SUM(G33:G34) -> 0.0049404006

Sheet DividendLek
B2: Vanguard FTSE All-World | C2: 2014 | D2: 2015 | E2: 2016 | F2: 2017 | G2: 2018 | H2: 2019 | I2: gemiddeld
B3: Dividend income | C3: 7496554 | D3: 17837465 | E3: 25181502 | F3: 28329734 | G3: 43044701 | H3: 64119281
B4: Foreign Withholding Tax | C4: 734078 | D4: 1970630 | E4: 3037267 | F4: 3337917 | G4: 5268891 | H4: 7444601
B5: Lek | C5: =C4/C3 -> 0.097922059 | D5: =D4/D3 -> 0.11047702 | E5: =E4/E3 -> 0.12061501 | F5: =F4/F3 -> 0.1178238 | G5: =G4/G3 -> 0.1224051 | H5: =H4/H3 -> 0.1161055 | I5: =AVERAGE(C5:H5) -> 0.11422475
B8: Global Stock Index Fund | C8: 2014 | D8: 2015 | E8: 2016 | F8: 2017 | G8: 2018 | H8: 2019 | I8: gemiddeld
B9: Dividends | C9: 231880154 | D9: 226198931 | E9: 223222039 | F9: 245815818 | G9: 274768506 | H9: 281441122
B10: Foreign Withholding Tax | C10: 39535737 | D10: 44341565 | E10: 41371984 | F10: 44756666 | G10: 49706758 | H10: 51221448
B11: Lek | C11: =C10/C9 -> 0.17050074 | D11: =D10/D9 -> 0.19602907 | E11: =E10/E9 -> 0.18534005 | F11: =F10/F9 -> 0.18207399 | G11: =G10/G9 -> 0.18090413 | H11: =H10/H9 -> 0.18199703 | I11: =AVERAGE(C11:H11) -> 0.1828075
B14: Global Small-Cap Index Fund | C14: 2014 | D14: 2015 | E14: 2016 | F14: 2017 | G14: 2018 | H14: 2019 | I14: gemiddeld
B15: Dividends | C15: 13944987 | D15: 15761605 | E15: 16231153 | F15: 23583250 | G15: 32845105 | H15: 44903246
B16: Foreign Withholding Tax | C16: 2565136 | D16: 2868270 | E16: 3422226 | F16: 4191552 | G16: 5957479 | H16: 8170665
B17: Lek | C17: =C16/C15 -> 0.18394682 | D17: =D16/D15 -> 0.18197829 | E17: =E16/E15 -> 0.21084306 | F17: =F16/F15 -> 0.17773428 | G17: =G16/G15 -> 0.18138103 | H17: =H16/H15 -> 0.18196157 | I17: =AVERAGE(C17:H17) -> 0.18630751
B20: Emerging Markets Stock Index Fund | C20: 2014 | D20: 2015 | E20: 2016 | F20: 2017 | G20: 2018 | H20: 2019 | I20: gemiddeld
B21: Dividends | C21: 201401546 | D21: 184653314 | E21: 191368175 | F21: 244455039 | G21: 282044286 | H21: 279075341
B22: Foreign Withholding Tax | C22: 15487001 | D22: 18051966 | E22: 21509558 | F22: 27381329 | G22: 33421807 | H22: 32065881
B23: Lek | C23: =C22/C21 -> 0.076896138 | D23: =D22/D21 -> 0.097761397 | E23: =E22/E21 -> 0.11239882 | F23: =F22/F21 -> 0.11200967 | G23: =G22/G21 -> 0.11849844 | H23: =H22/H21 -> 0.11490045 | I23: =AVERAGE(C23:H23) -> 0.10541082

Sheet Dividend
C3: 2019 | D3: 2018 | E3: 2017 | F3: 2016 | G3: 2015 | H3: 2014 | I3: 2013 | J3: 2012 | K3: 2011 | L3: 2010 | N3: Gemiddeld dividend na lek
B4: VWRL | C4: 0.0255 | D4: 0.0187 | E4: 0.0243 | F4: 0.0227 | G4: 0.0193 | H4: 0.0233 | I4: 0.0245 | N4: =AVERAGE(C4:M4) -> 0.022614286
B6: Emerging (GBP) | C6: 0.0271 | D6: 0.0225 | E6: 0.0227 | F6: 0.0284 | G6: 0.0233 | H6: 0.0229 | I6: 0.0207 | J6: 0.0229 | K6: 0.0181 | L6: 0.0146 | N6: =AVERAGE(C6:M6) -> 0.02232
B9: Small cap (GBP) | C9: 0.0184 | D9: 0.0131 | E9: 0.0148 | F9: 0.0196 | G9: 0.014 | H9: 0.0134 | I9: 0.0175 | J9: 0.0184 | K9: 0.0126 | N9: =AVERAGE(C9:M9) -> 0.015755556
