Workbook

Sheet MarketCap
B3: FTSE Global All-Cap | C3: 58928125
B4: FTSE All-World | C4: 53022086 | D4: =C4/C3 -> 0.89977555
B7: Toekomst | C7: Kosten met lek | D7: Kosten zonder lek | E7: TD | F7: Lek
B8: VWRL | C8: =VWRL!C41 -> 0.0052401836 | D8: =VWRL!C42 -> 0.0021316412 | E8: =VWRL!C45 -> 0.0048882889 | F8: =VWRL!J18 -> 0.11422475
B10: VWRL met 2,5% dividend | C10: =D8+(F8*2.5%) -> 0.0049872599

Sheet VWRL
B2: Vanguard FTSE All-World UCITS ETF
B3: 05-2012 gestart
C4: 2013 | D4: 2014 | E4: 2015 | F4: 2016 | G4: 2017 | H4: 2018 | I4: 2019 | J4: Gemiddelde | M4: Kosten uit https://global.vanguard.com/portal/site/loadPDF?country=global&docId=15835
B5: Net asset value einde boekjaar | C5: 114950407 | D5: 474931514 | E5: 876937458 | F5: 937471365 | G5: 1295979632 | H5: 2102651548 | I5: 2704960870 | M5: 0,02% transaction costs
B6: Management Fees (TER) | D6: 615977 | E6: 1698292 | F6: 2296151 | G6: 2711104 | H6: 4167659 | I6: 5770056 | M6: Check, kan als het vermogen zo blijft
B7: TER gemeld | D7: 0.0025 | E7: 0.0025 | F7: 0.0025 | G7: 0.0025 | H7: 0.0025 | I7: 0.0025 | J7: =AVERAGE(D7:I7) -> 0.0025
B8: Gemiddeld vermogen | D8: =(C5+D5)/2 -> 2.9494096e+08 | E8: =(D5+E5)/2 -> 675934486 | F8: =(E5+F5)/2 -> 9.0720441e+08 | G8: =(F5+G5)/2 -> 1.1167255e+09 | H8: =(G5+H5)/2 -> 1699315590 | I8: =(H5+I5)/2 -> 2403806209 | M8: Forse rente inkomsten laatste jaren
B9: Gemiddeld vermogen via TER | D9: =D6/D7 -> 246390800 | E9: =E6/E7 -> 679316800 | F9: =F6/F7 -> 918460400 | G9: =G6/G7 -> 1084441600 | H9: =H6/H7 -> 1667063600 | I9: =I6/I7 -> 2308022400
B11: Rente | D11: 693 | E11: 1325 | F11: 6885 | G11: 36075 | H11: 208125 | I11: 542060
B12: Overige inkomsten | D12: 2527 | E12: 2832 | F12: 13695 | G12: 1260 | H12: 6198 | I12: 0
B13: Rente en overig inkomsten | D13: =SUM(D11:D12) -> 3220 | E13: =SUM(E11:E12) -> 4157 | F13: =SUM(F11:F12) -> 20580 | G13: =SUM(G11:G12) -> 37335 | H13: =SUM(H11:H12) -> 214323 | I13: =SUM(I11:I12) -> 542060
B14: % | D14: =D13/D9 -> 1.306867e-05 | E14: =E13/E9 -> 6.1193835e-06 | F14: =F13/F9 -> 2.2407063e-05 | G14: =G13/G9 -> 3.4427857e-05 | H14: =H13/H9 -> 0.00012856318 | I14: =I13/I9 -> 0.00023485907 | J14: =AVERAGE(D14:I14) -> 7.3240871e-05
B16: Dividend income | D16: 7496554 | E16: 17837465 | F16: 25181502 | G16: 28329734 | H16: 43044701 | I16: 64119281
B17: Foreign Withholding Tax | D17: 734078 | E17: 1970630 | F17: 3037267 | G17: 3337917 | H17: 5268891 | I17: 7444601
B18: Dividend lek | D18: =D17/D16 -> 0.097922059 | E18: =E17/E16 -> 0.11047702 | F18: =F17/F16 -> 0.12061501 | G18: =G17/G16 -> 0.1178238 | H18: =H17/H16 -> 0.1224051 | I18: =I17/I16 -> 0.1161055 | J18: =AVERAGE(D18:I18) -> 0.11422475
B19: % dividend lek | D19: =D17/D9 -> 0.0029793239 | E19: =E17/E9 -> 0.0029008998 | F19: =F17/F9 -> 0.0033069112 | G19: =G17/G9 -> 0.0030780053 | H19: =H17/H9 -> 0.0031605819 | I19: =I17/I9 -> 0.0032255324 | J19: =AVERAGE(D19:I19) -> 0.0031085424
B21: Interest expense | D21: 0 | E21: 158 | F21: 1396 | G21: 2885 | H21: 9018 | I21: 5758
B22: Other expenses | D22: 9869 | E22: 21633 | F22: 10148 | G22: 13195 | H22: 12842 | I22: 2048
B23: % | D23: =(D22+D21)/D9 -> 4.0054255e-05 | E23: =(E22+E21)/E9 -> 3.2077817e-05 | F23: =(F22+F21)/F9 -> 1.256886e-05 | G23: =(G22+G21)/G9 -> 1.4827908e-05 | H23: =(H22+H21)/H9 -> 1.3112877e-05 | I23: =(I22+I21)/I9 -> 3.3821162e-06 | J23: =AVERAGE(D23:I23) -> 1.9337306e-05
B25: Secuties lended | G25: 984905 | H25: 3201782 | I25: 7704750
G26: =G25/G5 -> 0.00075996951 | H26: =H25/H5 -> 0.0015227354 | I26: =I25/I5 -> 0.0028483776
B28: Securities lending income | G28: 44238 | H28: 121589 | I28: 263359
B29: % lending income | D29: =D28/D9 -> 0 | E29: =E28/E9 -> 0 | F29: =F28/F9 -> 0 | G29: =G28/G9 -> 4.0793345e-05 | H29: =H28/H9 -> 7.293603e-05 | I29: =I28/I9 -> 0.00011410591 | J29: =AVERAGE(D29:I29) -> 3.7972548e-05
B31: Transaction Fees and Commissions | D31: 282714 | E31: 332383 | F31: 250041 | G31: 214668 | H31: 556031 | I31: 394506
B32: % transactie kosten | D32: =D31/D9 -> 0.0011474211 | E32: =E31/E9 -> 0.00048929012 | F32: =F31/F9 -> 0.00027223928 | G32: =G31/G9 -> 0.00019795257 | H32: =H31/H9 -> 0.00033353916 | I32: =I31/I9 -> 0.00017092815 | J32: =AVERAGE(D32:I32) -> 0.0004352284
B34: Derivaten | E34: 0.0001 | F34: 0 | G34: 0 | H34: 0.0002 | I34: 0.0002
B37: Kosten benadering verleden | C37: =J7+J19-J29+J32-J14+J23 -> 0.0059518947
B38: Tracking difference | C38: =TD!K5/100 -> 0.0056
B39: Gat | C39: =C38-C37 -> -0.00035189471
B41: Schatting kosten toekomst | C41: =0.22%-H14+J19-I29+I32+I23 -> 0.0052401836
B42: Kosten toekomst zonder lek | C42: =0.22%-H14-I29+I32+I23 -> 0.0021316412
B44: Kosten verschil toekomst en heden | C44: =C41-C37 -> -0.00071171111
B45: Schatting toekomst tracking diff | C45: =C38+C44 -> 0.0048882889

Sheet TD
C1: 2013 | D1: 2014 | E1: 2015 | F1: 2016 | G1: 2017 | H1: 2018 | I1: 2019 | K1: TD | L1: OPNI
B2: Vanguard VWRL | C2: 22.82 | D2: 4.28 | E2: -2.23 | F2: 7.98 | G2: 23.98 | H2: -9.62 | I2: 26.57
B3: FTSE All-World Index gross | C3: 23.3 | D3: 4.8 | E3: -1.7 | F3: 8.6 | G3: 24.6 | H3: -9.1 | I3: 27.2
B4: FTSE All-World Index NET | C4: 22.69 | D4: 4.23 | E4: -2.17 | F4: 8 | G4: 23.97 | H4: -9.57 | I4: 26.52
B5: Vs gross | C5: =C3-C2 -> 0.48 | D5: =D3-D2 -> 0.52 | E5: =E3-E2 -> 0.53 | F5: =F3-F2 -> 0.62 | G5: =G3-G2 -> 0.62 | H5: =H3-H2 -> 0.52 | I5: =I3-I2 -> 0.63 | K5: =AVERAGE(C5:I5) -> 0.56
B6: Vs net | C6: =C2-C4 -> 0.13 | D6: =D2-D4 -> 0.05 | E6: =E2-E4 -> -0.06 | F6: =F2-F4 -> -0.02 | G6: =G2-G4 -> 0.01 | H6: =H2-H4 -> -0.05 | I6: =I2-I4 -> 0.05 | L6: =AVERAGE(C6:I6) -> 0.015714286

Sheet DividendLekkage
C1: 2014 | D1: 2015 | E1: 2016 | F1: 2017 | G1: 2018 | H1: 2019 | J1: Gem
B2: Vanguard DAX | H2: =37489/296356 -> 0.12649989 | J2: =AVERAGE(C2:H2) -> 0.12649989
B3: Vanguard FTSE 100 | C3: =87602/47464893 -> 0.0018456167 | D3: =568633/61443719 -> 0.0092545342 | E3: =1476432/105359240 -> 0.014013313 | F3: =895025/81673540 -> 0.010958567 | G3: =1522926/110267237 -> 0.013811228 | H3: =1667965/126621109 -> 0.013172883 | J3: =AVERAGE(C3:H3) -> 0.010509357
B4: Vanguard FTSE All-World | J4: =VWRL!J18 -> 0.11422475
B5: Vanguard FTSE All-World High Dividend Yield | C5: =276998/3363386 -> 0.082356887 | D5: =993993/9974527 -> 0.099653146 | E5: =1526539/14343861 -> 0.10642455 | F5: =1933590/18057679 -> 0.10707855 | G5: =2658425/25206083 -> 0.1054676 | H5: =3332714/30787587 -> 0.10824863 | J5: =AVERAGE(C5:H5) -> 0.10153823
B6: Vanguard FTSE Developed Asia Pacific ex Japan | C6: =38753/1151217 -> 0.033662637 | D6: =95674/2910412 -> 0.032873009 | E6: =135521/3697627 -> 0.036650803 | F6: =217184/6020134 -> 0.036076273 | G6: =396984/12310610 -> 0.032247305 | H6: =725905/14080736 -> 0.051553058 | J6: =AVERAGE(C6:H6) -> 0.037177181
B7: Vanguard FTSE Developed Europe | C7: =449779/6453840 -> 0.069691687 | D7: =98042/1768698 -> 0.055431736 | E7: =1214196/16699948 -> 0.072706574 | F7: =2137859/28612288 -> 0.074718212 | G7: =4211322/55451908 -> 0.075945484 | H7: =4497447/63355725 -> 0.070987223 | J7: =AVERAGE(C7:H7) -> 0.069913486
B8: Vanguard FTSE Developed Europe ex UK | D8: =146930/1398033 -> 0.10509766 | E8: =721453/6516531 -> 0.11071121 | F8: =1277534/12552233 -> 0.10177743 | G8: =3575141/33665380 -> 0.10619637 | H8: =3893883/38411323 -> 0.10137331 | J8: =AVERAGE(C8:H8) -> 0.10503119
B9: Vanguard FTSE Developed World | D9: =66149/572890 -> 0.11546545 | E9: =156844/1316266 -> 0.11915829 | F9: =255100/2129637 -> 0.11978567 | G9: =487837/3930173 -> 0.12412609 | H9: =877262/7446153 -> 0.11781412 | J9: =AVERAGE(C9:H9) -> 0.11926992
B10: Vanguard FTSE Emerging Markets | C10: =298586/3325881 -> 0.089776513 | D10: =1274164/13386831 -> 0.095180405 | E10: =1706810/17405209 -> 0.098063172 | F10: =3013440/29020960 -> 0.10383668 | G10: =4856073/44723633 -> 0.10857957 | H10: =5576288/55691122 -> 0.10012885 | J10: =AVERAGE(C10:H10) -> 0.099260865
B11: Vanguard FTSE Japan | C11: =160529/1233458 -> 0.13014549 | D11: =1532098/10217727 -> 0.14994509 | E11: =2439137/16266986 -> 0.149944 | F11: =2650584/17759481 -> 0.14924896 | G11: =5929674/39527484 -> 0.15001395 | H11: =6964518/46429139 -> 0.15000317 | J11: =AVERAGE(C11:H11) -> 0.14655011
B12: Vanguard FTSE North America | D12: =39362/256875 -> 0.15323406 | E12: =65794/408533 -> 0.16104941 | F12: =133040/825605 -> 0.16114243 | G12: =433061/2477912 -> 0.17476851 | H12: =689318/4448721 -> 0.15494746 | J12: =AVERAGE(C12:H12) -> 0.16102838
B13: Vanguard S&P 500 | C13: =7721652/52371805 -> 0.1474391 | D13: =27863194/196059743 -> 0.14211583 | E13: =41287532/271884091 -> 0.15185711 | F13: =52477342/354919338 -> 0.14785709 | G13: =62709293/420900920 -> 0.14898825 | H13: =79389011/484099232 -> 0.16399326 | J13: =AVERAGE(C13:H13) -> 0.15037511

Sheet Dividend
C3: 2019 | D3: 2018 | E3: 2017 | F3: 2016 | G3: 2015 | H3: 2014 | I3: 2013 | J3: 2012 | K3: 2011 | L3: 2010 | M3: 2009 | N3: 2008 | O3: 2007 | P3: 2006 | Q3: 2005 | S3: Gemiddeld dividend na lek | T3: Lek | U3: Bruto dividend
B4: VWRL | C4: 0.0255 | D4: 0.0187 | E4: 0.0243 | F4: 0.0227 | G4: 0.0193 | H4: 0.0233 | I4: 0.0245 | S4: =AVERAGE(C4:M4) -> 0.022614286 | T4: =(100-(VWRL!J18*100))/100 -> 0.88577525 | U4: =S4/T4 -> 0.025530501
B6: Emerging Fund (GBP) | C6: 0.0271 | D6: 0.0225 | E6: 0.0227 | F6: 0.0284 | G6: 0.0233 | H6: 0.0229 | I6: 0.0207 | J6: 0.0229 | K6: 0.0181 | L6: 0.0146 | S6: =AVERAGE(C6:M6) -> 0.02232 | T6: =(100-(#REF!*100))/100 -> #REF! | U6: =S6/T6 -> #REF!
B9: Small cap Fund (GBP) | C9: 0.0184 | D9: 0.0131 | E9: 0.0148 | F9: 0.0196 | G9: 0.014 | H9: 0.0134 | I9: 0.0175 | J9: 0.0184 | K9: 0.0126 | S9: =AVERAGE(C9:M9) -> 0.015755556 | T9: =1-0.18 -> 0.82 | U9: =S9/T9 -> 0.019214092
B11: Vanguard VT | C11: 0.0309 | D11: 0.0209 | E11: 0.0275 | F11: 0.0266 | G11: 0.023 | H11: 0.0247 | I11: 0.0276 | J11: 0.0268 | K11: 0.0216 | L11: 0.0216 | M11: 0.0202 | S11: =AVERAGE(C11:M11) -> 0.024672727 | T11: =(100-5.3)/100 -> 0.947 | U11: =S11/T11 -> 0.026053566
B13: VTI | C13: 0.0247 | D13: 0.018 | E13: 0.0219 | F13: 0.0226 | G13: 0.0196 | H13: 0.0204 | I13: 0.0256 | J13: 0.0249 | K13: 0.0194 | L13: 0.0223 | M13: 0.029 | N13: 0.0138 | O13: 0.0185 | P13: 0.0201 | Q13: 0.0183 | S13: =AVERAGE(C13:Q13) -> 0.021273333 | U13: =S13 -> 0.021273333
B14: VXUS | C14: 0.0381 | D14: 0.0245 | E14: 0.0364 | F14: 0.031 | G14: 0.025 | H14: 0.0299 | I14: 0.0335 | J14: 0.0352 | S14: =AVERAGE(C14:Q14) -> 0.0317 | T14: =(100-6)/100 -> 0.94 | U14: =S14/T14 -> 0.033723404
