Workbook

Sheet AVWC
A1: Avantis Global Equity UCITS ETF
B3: 2025 | D3: AVG
A4: AUM end of bookyear | B4: 450218020
A5: TER | B5: 0.0022
A6: Operating Expenses | B6: 735849
A7: Average AUM | B7: =B6/B5 -> 3.3447682e+08
A9: Dividend income | B9: 6443236
A10: Foreign Withholding Tax | B10: 814806
A11: Dividend leakage | B11: =B10/B9 -> 0.12645913 | D11: =AVERAGE(B11:B11) -> 0.12645913
A12: % dividend | B12: =B9/B7 -> 0.019263625 | D12: =AVERAGE(B12:B12) -> 0.019263625
A13: % dividend leakage costs | B13: =B10/B7 -> 0.0024360612 | D13: =AVERAGE(B13:B13) -> 0.0024360612
A15: Securities lending income | B15: 0
A16: % lending income | B16: =B15/B7 -> 0
A17: Securities on loan | B17: 0
A19: Transaction costs | B19: 134610
A20: Transaction costs % | B20: =B19/B7 -> 0.00040244942 | D20: =AVERAGE(B20:B20) -> 0.00040244942
A22: KIID stated transaction costs | B22: 0.0001
A24: AVWC | B24: =B3 -> 2025
A25: =A5 -> TER | B25: =B5 -> 0.0022
A26: =A11 -> Dividend leakage | B26: =B13 -> 0.0024360612
A27: =A19 -> Transaction costs | B27: =B20 -> 0.00040244942
A28: Lending income | B28: =B16 -> 0
A29: Total | B29: =SUM(B25:B28) -> 0.0050385106

Sheet AVWS
A1: Avantis Global Small Cap Value UCITS ETF
B3: 2025 | D3: AVG
A4: AUM end of bookyear | B4: 843294218
A5: TER | B5: 0.0039
A6: Operating Expenses | B6: 1746350
A7: Average AUM | B7: =B6/B5 -> 4.4778205e+08
A9: Dividend income | B9: 10990095
A10: Foreign Withholding Tax | B10: 1279263
A11: Dividend leakage | B11: =B10/B9 -> 0.11640145 | D11: =AVERAGE(B11:B11) -> 0.11640145
A12: % dividend | B12: =B9/B7 -> 0.024543402 | D12: =AVERAGE(B12:B12) -> 0.024543402
A13: % dividend leakage costs | B13: =B10/B7 -> 0.0028568876 | D13: =AVERAGE(B13:B13) -> 0.0028568876
A15: Securities lending income | B15: 0
A16: % lending income | B16: =B15/B7 -> 0
A17: Securities on loan | B17: 0
A19: Transaction costs | B19: 404112
A20: Transaction costs % | B20: =B19/B7 -> 0.00090247476 | D20: =AVERAGE(B20:B20) -> 0.00090247476
A22: KIID stated transaction costs | B22: 0
A24: AVWS | B24: =B3 -> 2025
A25: =A5 -> TER | B25: =B5 -> 0.0039
A26: =A11 -> Dividend leakage | B26: =B13 -> 0.0028568876
A27: =A19 -> Transaction costs | B27: =B20 -> 0.00090247476
A28: Lending income | B28: =B16 -> 0
A29: Total | B29: =SUM(B25:B28) -> 0.0076593624

Sheet AVEM
A1: Avantis Emerging Markets Equity UCITS ETF
B3: 2025 | D3: AVG
A4: AUM end of bookyear | B4: 113897172
A5: TER | B5: 0.0035
A6: Operating Expenses | B6: 195814
A7: Average AUM | B7: =B6/B5 -> 55946857
A9: Dividend income | B9: 1691371
A10: Foreign Withholding Tax | B10: =215395 -> 215395
A11: Dividend leakage | B11: =B10/B9 -> 0.12734935 | D11: =AVERAGE(B11:B11) -> 0.12734935
A12: % dividend | B12: =B9/B7 -> 0.030231743 | D12: =AVERAGE(B12:B12) -> 0.030231743
A13: % dividend leakage costs | B13: =B10/B7 -> 0.0038499929 | D13: =AVERAGE(B13:B13) -> 0.0038499929
A15: Capital gains tax | B15: 169763
A16: % capital gains tax costs | B16: =B15/B7 -> 0.0030343617
A18: Securities lending income | B18: 0
A19: % lending income | B19: =B18/B7 -> 0
A20: Securities on loan | B20: 0
A22: Transaction costs | B22: 219809
A23: Transaction costs % | B23: =B22/B7 -> 0.0039288891 | D23: =AVERAGE(B23:B23) -> 0.0039288891
A25: KIID stated transaction costs | B25: 0.0003
A27: AVEM | B27: =B3 -> 2025
A28: =A5 -> TER | B28: =B5 -> 0.0035
A29: =A11 -> Dividend leakage | B29: =B13 -> 0.0038499929
A30: =A22 -> Transaction costs | B30: =B23 -> 0.0039288891
A31: Lending income | B31: =B19 -> 0
A32: =A15 -> Capital gains tax | B32: =B16 -> 0.0030343617
A33: Total | B33: =SUM(B28:B32) -> 0.014313244

Sheet RR C-P
C2: =AVWC!A24 -> AVWC | D2: =AVWS!A24 -> AVWS | E2: =AVEM!A27 -> AVEM
B3: =AVWC!A25 -> TER | C3: =AVWC!B25 -> 0.0022 | D3: =AVWS!B25 -> 0.0039 | E3: =AVEM!B28 -> 0.0035
B4: =AVWC!A26 -> Dividend leakage | C4: =AVWC!B26 -> 0.0024360612 | D4: =AVWS!B26 -> 0.0028568876 | E4: =AVEM!B29 -> 0.0038499929
B5: =AVEM!A32 -> Capital gains tax | C5: 0 | D5: 0 | E5: =AVEM!B32 -> 0.0030343617
B6: =AVWC!A27 -> Transaction costs | C6: =AVWC!B27 -> 0.00040244942 | D6: =AVWS!B27 -> 0.00090247476 | E6: =AVEM!B30 -> 0.0039288891
B7: =AVWC!A28 -> Lending income | C7: =AVWC!B28 -> 0 | D7: =AVWS!B28 -> 0 | E7: =AVEM!B31 -> 0
B8: =AVWC!A29 -> Total | C8: =AVWC!B29 -> 0.0050385106 | D8: =AVWS!B29 -> 0.0076593624 | E8: =AVEM!B33 -> 0.014313244
