Workbook

Sheet Aannames
B2: Aannames
B3: Jaarverslag: The OCF includes the cost of
B4: management
B5: investment management and administration of the Sub-Funds
B6: plus other running costs, such as depositary, audit and regulatory fees.
B7: Transaction costs and interest expenses are excluded from the calculation.
B9: Transaction costs are costs incurred to acquire or dispose of financial assets or liabilities at fair value through profit or loss. They include fees and commissions paid to agents, brokers and dealers. Transaction costs for the year are disclosed in the Statement of Comprehensive Income.
B13: Doe de aanname wat in het jaarverslag onder "other expenses" staat dus in de TER/OCF zit
B14: Lijkt wel te kloppen als ik alle kosten ex transactie optel. Kom dan wel bij de TER in de buurt
B15: Rente kosten neem ik niet mee, meestal weinig. En ook weer rente inkomsten.
B17: Dat transactie en rentekosten van feeder en master fonds bij elkaar opgeteld moeten worden
B18: Bij de world feeder worden er namelijk bijna geen kosten gemeld
... B28: Allen maar 1x per jaar dividend uitkering, lopende dividenden worden wel meteen geinvesteerd?

Sheet MarketCap
B2: MSCI ACWI IMI | C2: 53732257
G4: Uitsluitingen | K4: Kosten
B5: MSCI World | C5: 41819773 | F5: NT World | G5: 0.055 | H5: =C5*(100%-G5) -> 39519685 | I5: =H5/$H$8 -> 0.7999545 | K5: =World!C27 -> 0.0027994627 | L5: =I5*K5 -> 0.0022394428
B6: MSCI World SC | C6: 5480574.1 | F6: NT Small | G6: 0.177 | H6: =C6*(100%-G6) -> 4510512.5 | I6: =H6/$H$8 -> 0.091301455 | K6: =Emerging!C20 -> 0.0032179251 | L6: =I6*K6 -> 0.00029380124
B7: MSCI Emerging | C7: 5789028.7 | F7: NT Em | G7: 0.072 | H7: =C7*(100%-G7) -> 5372218.6 | I7: =H7/$H$8 -> 0.10874404 | K7: =SmallCaps!C20 -> 0.0039817641 | L7: =I7*K7 -> 0.00043299314
B8: EM small caps | C8: 642881.35 | D8: + | H8: =SUM(H5:H7) -> 49402417 | L8: =SUM(L5:L7) -> 0.0029662372
B9: cross check | C9: =SUM(C5:C8) -> 53732257 | H9: =SUM(H5:H7)/C2 -> 0.91941823
G11: Uitsluitingen
F12: NT World | G12: 0.055 | H12: =C5*(100%-G12) -> 39519685
F13: NT Em | G13: 0.072 | H13: =C7*(100%-G13) -> 5372218.6
H16: =SUM(H12:H13)/C2 -> 0.83547401

Sheet World
B2: Northern Trust World Custom ESG Equity Index UCITS FGR Feeder Fund € | J2: Wat valt op
B3: 09-2015 gestart. Feeder naar: Northern Trust World Custom ESG Equity Index Fund | J3: De TER heeft veel gewisseld, world wordt duurder als er meer vermogen in zit. Raar
C4: 2016 | D4: 2017 | E4: 2018 | F4: 2019 | H4: Gemiddelde | J4: Of in begin gewoon goedkoop geweest om vermogen aan te trekken?
B5: Transaction costs | C5: 0 | D5: 0 | E5: 0 | F5: 22294 | J5: Op de 2017 factsheet adverteerde men wel met een 0.15% TER
B6: Average net asset value | C6: 607319449 | D6: 1151302913 | E6: 1781058053 | F6: 2673847808
B7: % transactie kosten feeder | C7: =C5/C6 -> 0 | D7: =D5/D6 -> 0 | E7: =E5/E6 -> 0 | F7: =F5/F6 -> 8.3377969e-06 | J7: In de start jaren vaak wat hogere transactiekosten
B8: % transactie kosten master | C8: ='Northern Trust Master fondsen'!D6 -> 0.00013528648 | D8: ='Northern Trust Master fondsen'!E6 -> 4.4782844e-05 | E8: ='Northern Trust Master fondsen'!F6 -> 4.230011e-05 | F8: ='Northern Trust Master fondsen'!G6 -> 4.6130036e-05
B9: % transactie kosten totaal | C9: =SUM(C7:C8) -> 0.00013528648 | D9: =SUM(D7:D8) -> 4.4782844e-05 | E9: =SUM(E7:E8) -> 4.230011e-05 | F9: =SUM(F7:F8) -> 5.4467833e-05 | H9: =AVERAGE(C9:G9) -> 6.9209318e-05 | J9: De in rekening gebrachte TER lijkt soms lager als wat er in rekening gebracht had moeten worden
B10: TER | C10: 0.0003 | D10: 0.0003 | E10: 0.0012 | F10: 0.0015 | H10: =AVERAGE(C10:F10) -> 0.000825 | J10: Of de average net asset value klopt niet
B12: Operating costs | C12: 72708 | D12: 323257 | E12: 2280765 | F12: 3265001 | J12: Tussen de kosten benadering en tracking difference zit best een gat:
B13: Rente | C13: 1794 | D13: 4996 | E13: 7109 | F13: 31761 | J13: Dividend herinvestering drag?
B14: % OC | C14: =C12/C6 -> 0.00011971953 | D14: =D12/D6 -> 0.00028077493 | E14: =E12/E6 -> 0.0012805675 | F14: =F12/F6 -> 0.0012210871 | H14: =AVERAGE(C14:F14) -> 0.00072553725 | J14: Tax drag?
B15: % OC + Rente | C15: =(C12+C13)/C6 -> 0.0001226735 | D15: =(D12+D13)/D6 -> 0.00028511437 | E15: =(E12+E13)/E6 -> 0.0012845589 | F15: =(F12+F13)/F6 -> 0.0012329655 | H15: =AVERAGE(C15:F15) -> 0.00073132806 | J15: Toch nog wat dividend lekkage?
J16: Optimized selectie?
B17: Kosten gemiddeld | C17: =H9+H14 -> 0.00079474657 | D17: 2016-2019 | J17: Tracking Difference klopt niet door Swing pricing?
B18: Tracking difference | C18: ='Tracking Difference'!L6/100 -> 0.002025 | D18: 2016-2019 | J18: Feeder master structuur met cash drag?
B19: Gat met kosten benadering | C19: =C18-C17 -> 0.0012302534 | D19: 2016-2019
B21: Kosten gemiddeld | C21: =AVERAGE(E14:F14)+AVERAGE(E9:F9) -> 0.0012992112 | D21: 2018-2019
B22: Tracking difference | C22: ='Tracking Difference'!O6/100 -> 0.0021 | D22: 2018-2019
B23: Gat met kosten benadering | C23: =C22-C21 -> 0.00080078876 | D23: 2018-2019
B25: Schatting kosten toekomst | C25: =F10+H9 -> 0.0015692093 | D25: Huidige TER en transactiekosten
B27: Schatting tracking diff toekomst | C27: =C25+C19 -> 0.0027994627 | D27: 2016-2019 Alle kosten inc niet goed volgen index om onduidelijke redenen
B28: Schatting tracking diff toekomst | C28: =C25+C23 -> 0.0023699981 | D28: 2018-2019 Alle kosten inc niet goed volgen index om onduidelijke redenen

Sheet Emerging
B2: Northern Trust Emerging Markets Custom ESG Equity Index UCITS FGR Fund € | J2: Wat valt op
B3: 12-2015 gestart. Geen feeder | J3: TER wisselingen
C4: 2016 | D4: 2017 | E4: 2018 | F4: 2019 | H4: Gemiddelde | J4: In de start jaren vaak wat hogere transactiekosten
B5: Transaction costs | C5: 48346 | D5: 276690 | E5: 234574 | F5: 672683
B6: Average net asset value | C6: 41072828 | D6: 280855994 | E6: 798617793 | F6: 1521930963 | J6: De in rekening gebrachte TER lijkt soms anders als wat er in rekening gebracht had moeten worden
B7: % transactie kosten | C7: =C5/C6 -> 0.0011770799 | D7: =D5/D6 -> 0.0009851668 | E7: =E5/E6 -> 0.00029372499 | F7: =F5/F6 -> 0.00044199311 | H7: =AVERAGE(C7:F7) -> 0.0007244912
B8: TER | C8: 0.0028 | D8: 0.002 | E8: 0.0025 | F8: 0.0025 | H8: =AVERAGE(C8:F8) -> 0.00245 | J8: Tussen de kosten benadering en tracking difference zit een kleiner gat als bij world
B10: Operating costs | C10: 51166 | D10: 842623 | E10: 2541872 | F10: 4524697
B11: Rente | C11: 885 | D11: 35778 | E11: 15306 | F11: 11676
B12: % OC | C12: =C10/C6 -> 0.0012457384 | D12: =D10/D6 -> 0.0030001959 | E12: =E10/E6 -> 0.0031828392 | F12: =F10/F6 -> 0.0029729975 | H12: =AVERAGE(C12:F12) -> 0.0026004428
B13: % OC + Rente | C13: =(C10+C11)/C6 -> 0.0012672855 | D13: =(D10+D11)/D6 -> 0.003127585 | E13: =(E10+E11)/E6 -> 0.0032020048 | F13: =(F10+F11)/F6 -> 0.0029806694 | H13: =AVERAGE(C13:F13) -> 0.0026443862
B15: Kosten gemiddeld | C15: =H7+H12 -> 0.003324934 | D15: 2016-2019
B16: Tracking difference | C16: ='Tracking Difference'!L15/100 -> 0.003675 | D16: 2016-2019
B17: Gat met kosten benadering | C17: =C16-C15 -> 0.00035006605
B19: Schatting kosten toekomst | C19: =F8+AVERAGE(E7:F7) -> 0.002867859 | D19: TER en transactie
B20: Schatting tracking diff toekomst | C20: =C19+C17 -> 0.0032179251 | D20: Alle kosten inc eventueel lek en drag

Sheet SmallCaps
B2: Northern Trust World Small Cap ESG Low Carbon Index FGR Fund € | J2: Wat valt op
B3: 06-2019 gestart. Feeder naar Northern Trust World Small Cap ESG Low Carbon Index Fund
C4: 2016 | D4: 2017 | E4: 2018 | F4: 2019 | H4: Gemiddelde | J4: todo
B5: Transaction costs | F5: 2131
B6: Average net asset value | F6: 134685073
B7: % transactie kosten | F7: =F5/F6 -> 1.5822095e-05 | H7: =AVERAGE(F7) -> 1.5822095e-05
B8: % transactie kosten master | F8: ='Northern Trust Master fondsen'!G12 -> 0.00089319673 | H8: =AVERAGE(F8) -> 0.00089319673
B9: % transactie kosten totaal | F9: =SUM(F7:F8) -> 0.00090901883
B10: TER | F10: 0.0023 | H10: =AVERAGE(F10) -> 0.0023
B12: Operating costs | F12: todo
B13: Rente
B14: % OC
B15: % OC + Rente
B17: Kosten gemiddeld | C17: =SUM(H7:H10) -> 0.0032090188
B18: Schatting kosten toekomst | C18: Nog niet te geven vanwege transactiekosten en nu aan het opstarten is. Zal wat zakken tov nu, maar blijft wel small caps dus veel posities
B20: Gok kosten toekomst | C20: =F10+(75%*F9)+0.1% -> 0.0039817641

Sheet Northern Trust Master fondsen
B2: Northern Trust World Custom ESG Equity Index Fund US $ | I2: Deze getallen komen uit de "NORTHERN TRUST UCITS COMMON CONTRACTUAL FUND" jaarverslagen
C3: 2015 | D3: 2016 | E3: 2017 | F3: 2018 | G3: 2019
B4: Transaction costs | D4: 200474 | E4: 116789 | F4: 159626 | G4: 261252 | I4: Aannames
B5: Vermogen einde jaar | C5: 957946194 | D5: 2005749714 | E5: 3210042287 | F5: 4337266633 | G5: =6989496789 -> 6989496789 | I5: Er is ook een euro fonds world maar die is hedged en heeft dat ook in de naam, dat matched dus niet.
B6: % transactie kosten | D6: =D4/AVERAGE(C5:D5) -> 0.00013528648 | E6: =E4/AVERAGE(D5:E5) -> 4.4782844e-05 | F6: =F4/AVERAGE(E5:F5) -> 4.230011e-05 | G6: =G4/AVERAGE(F5:G5) -> 4.6130036e-05 | I6: Enkel deze naam matched volledig met de doorverwijzing vanuit het feeder fonds, wel $ is wat raar
I7: Neem dus aan dat het deze is. Gek, bij small caps is er wel gewoon een euro master fonds
B8: Northern Trust World Small Cap ESG Low Carbon Index Fund €
C9: 2015 | D9: 2016 | E9: 2017 | F9: 2018 | G9: 2019 | I9: Aannames
B10: Transaction costs | G10: 63179 | I10: Geen gemiddeld vermogen te vinden. Dus maar gemiddelde van stand begin en einde jaar. Aanname dat lineair oploopt.
B11: Vermogen einde jaar | F11: 0 | G11: 141467154 | I11: Is natuurlijk niet, maar heb niks anders
B12: % transactie kosten | G12: =G10/AVERAGE(F11:G11) -> 0.00089319673
I13: Bij iShares kan ik nog achteruit doordat de TER dagelijks in rekening wordt gebracht en er vermeld staat hoeveel er op jaarbasis
I14: in rekening is gebracht, bij NT is dat niet los te vinden, moet dan los gaan optellen wat er onder de TER valt van de kosten rekening
I15: zou preciezer zijn, maar de bedragen zijn zo laag dat het waarschijnlijk geen verschil maakt

Sheet Tracking Difference
C2: 2012 | D2: 2013 | E2: 2014 | F2: 2015 | G2: 2016 | H2: 2017 | I2: 2018 | J2: 2019 | L2: TD | M2: OPNI
B3: Northern trust World Custom ESG Equity | G3: 10.55 | H3: 8.32 | I3: -3.3 | J3: 30.93
B4: MSCI custom ESG (EUR) gross | E4: 20.76 | F4: 11.13 | G4: 10.72 | H4: 8.54 | I4: -3.12 | J4: 31.17
B5: MSCI custom ESG (EUR) net | G5: 10.07 | H5: 7.95 | I5: -3.65 | J5: 30.44
B6: Vs gross | G6: =G4-G3 -> 0.17 | H6: =H4-H3 -> 0.22 | I6: =I4-I3 -> 0.18 | J6: =J4-J3 -> 0.24 | L6: =AVERAGE(G6:J6) -> 0.2025 | O6: =AVERAGE(I6:J6) -> 0.21 | P6: TD 2018-2019
B7: Vs net | G7: =G3-G5 -> 0.48 | H7: =H3-H5 -> 0.37 | I7: =I3-I5 -> 0.35 | J7: =J3-J5 -> 0.49 | M7: =AVERAGE(G7:J7) -> 0.4225
B8: Bruto netto index verschil | G8: =G4-G5 -> 0.65 | H8: =H4-H5 -> 0.59 | I8: =I4-I5 -> 0.53 | J8: =J4-J5 -> 0.73 | O8: =AVERAGE(G8:J8) -> 0.625 | P8: gemiddeld bruto netto index verschil
D11: 2013 | E11: 2014 | F11: 2015 | G11: 2016 | H11: 2017 | I11: 2018 | J11: 2019 | L11: TD | M11: OPNI
B12: NORTHERN TRUST EMERGING MARKETS CUSTOM ESG EQUITY | G12: 12.94 | H12: 21.63 | I12: -10.75 | J12: 20.82
B13: MSCI custom ESG (EUR) gross | E13: 12.03 | F13: -3.64 | G13: 13.57 | H13: 21.71 | I13: -10.25 | J13: 21.08
B14: MSCI custom ESG (EUR) net | G14: 13.14 | H14: 21.3 | I14: -10.6 | J14: 20.61
B15: Vs gross | G15: =G13-G12 -> 0.63 | H15: =H13-H12 -> 0.08 | I15: =I13-I12 -> 0.5 | J15: =J13-J12 -> 0.26 | L15: =AVERAGE(G15:J15) -> 0.3675
B16: Vs net | G16: =G12-G14 -> -0.2 | H16: =H12-H14 -> 0.33 | I16: =I12-I14 -> -0.15 | J16: =J12-J14 -> 0.21 | M16: =AVERAGE(G16:J16) -> 0.0475
