Workbook

Sheet Aanames
B2: Aannames
B3: Gemiddeld vermogen via TER (operation expense) teruggerekend
B4: Helaas gemiddelde vermogen niet los te vinden via turnover oid
B6: Alles is x1000 wat hier aan cijfers staat
B8: "Dividend income" is bruto dividend. Denk dit omdat de belasting op de winst/verlies gewoon bij verlies is opgenomen.
B10: Rente kosten neem ik niet mee, meestal weinig. En ook weer rente inkomsten.
B11: Rente inkomsten zijn voor IWDA en EMIM tijdens 2016-2019 meestal hoger dan de kosten
B12: Als proef bij IWDA en EMIM rente inkomsten los bekeken, maar inkomsten zijn zeer beperkt

Sheet Totaal
B2: MSCI ACWI IMI | C2: 53732257
C4: Cap | D4: Market cap %
B5: MSCI World | C5: 41819773 | D5: 0.7782992
B6: MSCI World SC | C6: 5480574.1 | D6: 0.10199784
B7: MSCI Emerging | C7: 5789028.7 | D7: 0.10773842
B8: EM small caps | C8: 642881.35 | D8: 0.011964533
B9: cross check | C9: 53732257
B11: MSCI ACWI IMI - EM Small | C11: 53089376
B12: World + Emerging | C12: 47608802
B17: Toekomst | C17: Kosten met lek | D17: Kosten zonder lek | E17: TD | F17: Lek
B18: IWDA (Dev world) | C18: =IWDA!B29 -> 0.004881895 | D18: =IWDA!B31 -> 0.0019065611 | E18: =IWDA!B33 -> 0.0044563826 | F18: =IWDA!H12 -> 0.11634302
B19: EMIM (EM IMI) | C19: =EMIM!B28 -> 0.0047190583 | D19: =EMIM!B30 -> 0.0016460091 | E19: =EMIM!B32 -> 0.0039754294 | F19: =EMIM!G12 -> 0.12782731
B20: IEMM (EM Dist) | C20: =IEMM!B28 -> 0.0049214957 | E20: =IEMM!B31 -> 0.0049326425 | F20: =IEMM!H12 -> 0.12203009
B21: IEMA (EM Acc) | C21: =IEMA!B28 -> 0.0057099486 | E21: =IEMA!B31 -> 0.0050578331 | F21: =IEMA!H12 -> 0.12818992
B22: IEMS (EM Small) | C22: =IEMS!B28 -> 0.006819671 | E22: =IEMS!B31 -> 0.0046282955 | F22: =IEMS!H12 -> 0.14642302
B23: IUSN (Dev world small) | C23: =IUSN!B28 -> 0.0062892365 | D23: =IUSN!B29 -> 0.0035389714 | E23: =IUSN!B31 -> 0.0057892365 | F23: =IUSN!D12 -> 0.12574925
B26: IWDA + EMIM + IUSN
B27: Kosten | C27: =C18*D5+C19*(D7+D8)+C23*D6 -> 0.0050059488
B28: TD | C28: =E18*D5+E19*(D7+D8)+E23*D6 -> 0.0045347593
B30: IWDA + EMIM + IUSN 2,5% dividend
B31: Kosten zonder lek | C31: =D18*D5+D19*(D7+D8)+D23*D6 -> 0.0020418746
B32: Gem dividend lek | C32: =(F18*D5+F19*(D7+D8)+F23*D6)*2.5% -> 0.0029669285 | D32: +
B33: Kosten totaal | C33: =SUM(C31:C32) -> 0.0050088031

Sheet IWDA
A2: iShares Core MSCI World (IWDA) | J2: Wat valt op
A3: 09-2009 gestart | J3: De TER gaat weinig omlaag ook al neemt het vermogen fors toe
B4: 2014 | C4: 2015 | D4: 2016 | E4: 2017 | F4: 2018 | G4: 2019 | H4: Gemiddelde | J4: Lek vrij consistent
A5: Net asset value einde boekjaar | B5: 1487510 | C5: 4268212 | D5: 6473287 | E5: 10938731 | F5: 14711738 | G5: 19581640 | J5: Lending income beperkt
A6: Operating expense (TER) | B6: 3363 | C6: 5351 | D6: 10764 | E6: 17143 | F6: 26741 | G6: 34465 | J6: Transactiekosten zaken steeds verder naarmate vermogen toeneemt
A7: TER gemeld | B7: 0.0039 | C7: 0.002 | D7: 0.002 | E7: 0.002 | F7: 0.002 | G7: 0.002 | H7: =AVERAGE(B7:G7) -> 0.0023166667 | J7: Optimized selectie, maar heeft 1611/1637 posities
A8: Gemiddeld vermogen | B8: =B6/B7 -> 862307.69 | C8: =C6/C7 -> 2675500 | D8: =D6/D7 -> 5382000 | E8: =E6/E7 -> 8571500 | F8: =F6/F7 -> 13370500 | G8: =G6/G7 -> 17232500
J9: Mifid template 7130 ex ante transaction costs (0,01%) matched niet echt
A10: Dividend income | B10: 21877 | C10: 68989 | D10: 146778 | E10: 218802 | F10: 323631 | G10: 435291 | J10: Accumulerend, geen/weinig cash drag
A11: Taxation | B11: 2530 | C11: 7895 | D11: 17329 | E11: 25220 | F11: 37451 | G11: 51767
A12: Dividend lek | B12: =B11/B10 -> 0.11564657 | C12: =C11/C10 -> 0.11443853 | D12: =D11/D10 -> 0.11806265 | E12: =E11/E10 -> 0.11526403 | F12: =F11/F10 -> 0.1157213 | G12: =G11/G10 -> 0.11892504 | H12: =AVERAGE(B12:G12) -> 0.11634302 | J12: 4 basispunten er naast maar, niet onaardig
A13: % dividend lek | B13: =B11/B8 -> 0.0029339875 | C13: =C11/C8 -> 0.0029508503 | D13: =D11/D8 -> 0.0032198068 | E13: =E11/E8 -> 0.0029423088 | F13: =F11/F8 -> 0.0028010172 | G13: =G11/G8 -> 0.0030040331 | H13: =AVERAGE(B13:G13) -> 0.0029753339 | J13: wel gek dat ik meer kosten vind als de tracking difference
A14: Dividend | B14: =B10/B8 -> 0.025370294 | C14: =C10/C8 -> 0.025785461 | D14: =D10/D8 -> 0.027272018 | E14: =E10/E8 -> 0.025526687 | F14: =F10/F8 -> 0.024204854 | G14: =G10/G8 -> 0.025259887 | J14: komt door benadering gemiddeld fonds vermogen of omdat lending inkomsten meteen worden belegt
A16: Securities lending income | B16: 7 | C16: 349 | D16: 947 | E16: 2133 | F16: 3345 | G16: 5560
A17: % lending income | B17: =B16/B8 -> 8.117752e-06 | C17: =C16/C8 -> 0.00013044291 | D17: =D16/D8 -> 0.00017595689 | E17: =E16/E8 -> 0.00024884793 | F17: =F16/F8 -> 0.00025017763 | G17: =G16/G8 -> 0.00032264616 | H17: =AVERAGE(B17:G17) -> 0.00018936488
A18: Securities on loan | B18: =3/B5 -> 2.0167932e-06 | C18: =137586/C5 -> 0.032235044 | D18: =491894/D5 -> 0.075988288 | E18: 0.0778 | F18: 0.1073 | G18: 0.1256
A20: Transaction costs | B20: 611 | C20: 1652 | D20: 1649 | E20: 2396 | F20: 2254 | G20: 2701
A21: % transactie kosten | B21: =B20/B8 -> 0.00070856378 | C21: =C20/C8 -> 0.00061745468 | D21: =D20/D8 -> 0.00030639168 | E21: =E20/E8 -> 0.000279531 | F21: =F20/F8 -> 0.00016858008 | G21: =G20/G8 -> 0.00015673872 | H21: =AVERAGE(B21:G21) -> 0.00037287666
A23: Derivatives | C23: 0.0001 | D23: 0.0001 | E23: 0.0001 | F23: 0.0003 | G23: 0.0003
A25: Kosten benadering verleden | B25: =H7+H13-H17+H21 -> 0.0054755124 | C25: 2014-2019
A26: Tracking difference | B26: =TrackingDifference!L5/100 -> 0.00505 | C26: 2014-2019
A27: Gat met kosten benadering | B27: =B26-B25 -> -0.00042551239
A29: Schatting kosten toekomst | B29: =G7+H13-F17+G21 -> 0.004881895
A30: Verschil kosten toekomst en verleden | B30: =B29-B25 -> -0.00059361736
A31: Kosten toekomst zonder lek | B31: =G7-F17+G21 -> 0.0019065611
A33: Tracking diff toekomst | B33: =B26+B30 -> 0.0044563826
A35: Interest income | D35: 17 | E35: 163 | F35: 304 | G35: 1181
A36: % interest income | D36: =D35/D8 -> 3.1586771e-06 | E36: =E35/E8 -> 1.9016508e-05 | F36: =F35/F8 -> 2.2736622e-05 | G36: =G35/G8 -> 6.8533295e-05

Sheet EMIM
A2: iShares Core MSCI Emering Markets IMI UCITS ETF | I2: Wat valt op
A3: 05-2014 gestart | I3: 2019: During the financial year the TER of this Fund changed from 0.25% to 0.18%. The annualised TER for the year is 0.20%
B4: 2015 | C4: 2016 | D4: 2017 | E4: 2018 | F4: 2019 | G4: Gemiddelde
A5: Net asset value einde boekjaar | B5: 1055668 | C5: 1594449 | D5: 4605402 | E5: 9460691 | F5: 12495330 | I5: 2018 transactiekosten staan niet in jaarverslag
A6: Operating expense (TER) | B6: 763 | C6: 3182 | D6: 8100 | E6: 17606 | F6: 19891 | I6: Optimized selectie, heeft 2663/2941 posities
A7: TER gemeld | B7: 0.0025 | C7: 0.0025 | D7: 0.0025 | E7: 0.0025 | F7: 0.002 | G7: =AVERAGE(B7:F7) -> 0.0024 | I7: Accumulerend, geen/weinig cash drag
A8: Gemiddeld vermogen | B8: =B6/B7 -> 305200 | C8: =C6/C7 -> 1272800 | D8: =D6/D7 -> 3240000 | E8: =E6/E7 -> 7042400 | F8: =F6/F7 -> 9945500 | I8: Waarom is deze wel goedkoper geworden en IWDA niet?
A10: Dividend income | B10: 4988 | C10: 34764 | D10: 79612 | E10: 172015 | F10: 276851 | I10: 6 basispunten er naast maar, niet onaardig
A11: Taxation | B11: 661 | C11: 3983 | D11: 10068 | E11: 21696 | F11: 38608 | I11: wel gek dat ik meer kosten vind als de tracking difference
A12: Dividend lek | B12: =B11/B10 -> 0.13251804 | C12: =C11/C10 -> 0.11457255 | D12: =D11/D10 -> 0.12646335 | E12: =E11/E10 -> 0.12612854 | F12: =F11/F10 -> 0.13945407 | G12: =AVERAGE(B12:F12) -> 0.12782731 | I12: komt door benadering gemiddeld fonds vermogen of omdat lending inkomsten meteen worden belegt
A13: Dividend lek% | B13: =B11/B8 -> 0.0021657929 | C13: =C11/C8 -> 0.0031293212 | D13: =D11/D8 -> 0.0031074074 | E13: =E11/E8 -> 0.0030807679 | F13: =F11/F8 -> 0.0038819567 | G13: =AVERAGE(B13:F13) -> 0.0030730492
A15: Securities lending income | B15: 29 | C15: 610 | D15: 4933 | E15: 9146 | F15: 10433
A16: % lending income | B16: =B15/B8 -> 9.5019659e-05 | C16: =C15/C8 -> 0.00047925833 | D16: =D15/D8 -> 0.0015225309 | E16: =E15/E8 -> 0.001298705 | F16: =F15/F8 -> 0.0010490171 | G16: =AVERAGE(B16:F16) -> 0.0008889062
A17: Securities on loan | B17: =4406/B5 -> 0.0041736607 | C17: =95333/C5 -> 0.059790561 | D17: 0.1525 | E17: 0.1071 | F17: 0.1174
A19: Transaction costs | B19: 875 | C19: 1451 | D19: 2644 | F19: 5320
A20: % transactie kosten | B20: =B19/B8 -> 0.0028669725 | C20: =C19/C8 -> 0.0011400063 | D20: =D19/D8 -> 0.00081604938 | F20: =F19/F8 -> 0.00053491529 | G20: =AVERAGE(B20:F20) -> 0.0013394859
A22: Derivatives | B22: 0.0007 | C22: 0.0002 | D22: 0.0006 | E22: 0.0001 | F22: 0.0005
A24: Kosten benadering verleden | B24: =G7+G13-G16+G20 -> 0.0059236289 | C24: 2015-2019
A25: Tracking difference | B25: =TrackingDifference!L12/100 -> 0.00518 | C25: 2015-2019
A26: Gat met kosten benadering | B26: =B25-B24 -> -0.00074362888
A28: Schatting kosten toekomst | B28: =F7+G13-G16+F20 -> 0.0047190583
A29: Verschil kosten toekomst en verleden | B29: =B28-B24 -> -0.0012045706
A30: Kosten toekomst zonder lek | B30: =F7-G16+F20 -> 0.0016460091
A32: Tracking diff toekomst | B32: =B25+B29 -> 0.0039754294
A35: Interest income | C35: 4 | D35: 74 | E35: 302 | F35: 492
A36: % interest income | C36: =C35/C8 -> 3.1426776e-06 | D36: =D35/D8 -> 2.2839506e-05 | E36: =E35/E8 -> 4.2883108e-05 | F36: =F35/F8 -> 4.9469609e-05

Sheet IEMS
A2: iShares MSCI Emerging Markets Small Cap UCITS ETF | J2: Wat valt op
A3: 03-2009 gestart | J3: Vermogen loopt wat terug. Wel nog boven de 200 miljoen grens.
B4: 2014 | C4: 2015 | D4: 2016 | E4: 2017 | F4: 2018 | G4: 2019 | H4: Gemiddelde (2015-2019) | J4: TER blijft hoog
A5: Net asset value einde boekjaar | B5: 427535 | C5: 342236 | D5: 304119 | E5: 361091 | F5: 444594 | G5: 307508 | J5: Lending income hoog
A6: Operating expense (TER) | B6: 2914 | C6: 2987 | D6: 1990 | E6: 2533 | F6: 3152 | G6: 2713 | J6: Optimized selectie, maar heeft 1595/1640 posities
A7: TER gemeld | B7: 0.0074 | C7: 0.0074 | D7: 0.0074 | E7: 0.0074 | F7: 0.0074 | G7: 0.0074 | H7: =AVERAGE(C7:G7) -> 0.0074 | J7: 2x per jaar dividend, dus hier zal wat cash drag aanvullend op zitten
A8: Gemiddeld vermogen | B8: =B6/B7 -> 393783.78 | C8: =C6/C7 -> 403648.65 | D8: =D6/D7 -> 268918.92 | E8: =E6/E7 -> 342297.3 | F8: =F6/F7 -> 425945.95 | G8: =G6/G7 -> 366621.62 | J8: Dividend lek wisselt nogal
A10: Dividend income | B10: 9100 | C10: 9515 | D10: 6692 | E10: 7276 | F10: 9853 | G10: 9792 | J10: wel gek dat ik meer kosten vind als de tracking difference
A11: Taxation | B11: 1037 | C11: =1078+163 -> 1241 | D11: 742 | E11: 928 | F11: 1434 | G11: 2132 | J11: komt door benadering gemiddeld fonds vermogen of omdat lending inkomsten meteen worden belegt
A12: Dividend lek | B12: =B11/B10 -> 0.11395604 | C12: =C11/C10 -> 0.13042564 | D12: =D11/D10 -> 0.11087866 | E12: =E11/E10 -> 0.12754261 | F12: =F11/F10 -> 0.14553943 | G12: =G11/G10 -> 0.21772876 | H12: =AVERAGE(C12:G12) -> 0.14642302 | J12: laatste lijkt logischer, hoe meer lending inkomsten per fonds hoe groter het verschil is wat ik vind
A13: % dividend lek | B13: =B11/B8 -> 0.0026334248 | C13: =C11/C8 -> 0.003074456 | D13: =D11/D8 -> 0.002759196 | E13: =E11/E8 -> 0.0027110936 | F13: =F11/F8 -> 0.0033666244 | G13: =G11/G8 -> 0.0058152599 | H13: =AVERAGE(C13:G13) -> 0.0035453259 | J13: deze is de meest extreme
A15: Securities lending income | B15: 848 | C15: 1320 | D15: 1337 | E15: 1589 | F15: 2300 | G15: 2187
A16: % lending income | B16: =B15/B8 -> 0.002153466 | C16: =C15/C8 -> 0.0032701707 | D16: =D15/D8 -> 0.0049717588 | E16: =E15/E8 -> 0.0046421634 | F16: =F15/F8 -> 0.0053997462 | G16: =G15/G8 -> 0.0059652783 | H16: =AVERAGE(C16:G16) -> 0.0048498235
A17: Securities on loan | B17: =52694/B5 -> 0.12325073 | C17: =70814/C5 -> 0.2069157 | D17: =58576/D5 -> 0.19260881 | E17: 0.1374 | F17: 0.1503 | G17: 0.2161
A19: Transaction costs | B19: 622 | C19: 712 | D19: 349 | E19: 512 | F19: 405 | G19: 466
A20: % transactie kosten | B20: =B19/B8 -> 0.001579547 | C20: =C19/C8 -> 0.0017639103 | D20: =D19/D8 -> 0.0012977889 | E20: =E19/E8 -> 0.0014957758 | F20: =F19/F8 -> 0.00095082487 | G20: =G19/G8 -> 0.0012710652 | H20: =AVERAGE(C20:G20) -> 0.001355873
A22: Derivatives | C22: 0 | D22: 0.0005 | E22: 0 | F22: 0.0002 | G22: 0.0002
A24: Kosten benadering verleden | B24: =H7+H13-H16+H20 -> 0.0074513755 | C24: 2015-2019
A25: Tracking difference | B25: =TrackingDifference!L25/100 -> 0.00526 | C25: 2015-2019
A26: Gat met kosten benadering | B26: =B25-B24 -> -0.0021913755
A28: Schatting kosten toekomst | B28: =G7+AVERAGE(B13:G13)+G20-AVERAGE(D16:G16) -> 0.006819671
A29: Verschil kosten toekomst en verleden | B29: =B28-B24 -> -0.00063170448
A31: Tracking diff toekomst | B31: =B25+B29 -> 0.0046282955

Sheet IUSN
A2: iShares MSCI World Small Cap UCITS ETF | F2: Wat valt op
A3: 03-2018 gestart | F3: Nieuw, benieuwd naar 2020 cijfers
B4: 2018 | C4: 2019 | D4: Gemiddelde | F4: Optimized selectie, heeft 3303/4263 posities dus tracking diff bekijken geen nut
A5: Net asset value einde boekjaar | B5: 321064 | C5: 861947 | F5: Accumulerend, geen/weinig cash drag
A6: Operating expense (TER) | B6: 267 | C6: 1886
A7: TER gemeld | B7: 0.0035 | C7: 0.0035 | D7: =AVERAGE(B7:C7) -> 0.0035
A8: Gemiddeld vermogen | B8: =B6/B7 -> 76285.714 | C8: =C6/C7 -> 538857.14
A10: Dividend income | B10: 2314 | C10: 12293
A11: Taxation | B11: 303 | C11: 1482
A12: Dividend lek | B12: =B11/B10 -> 0.13094209 | C12: =C11/C10 -> 0.12055641 | D12: =AVERAGE(B12:C12) -> 0.12574925
A13: Dividend lek% | B13: =B11/B8 -> 0.0039719101 | C13: =C11/C8 -> 0.0027502651 | D13: =AVERAGE(B13:C13) -> 0.0033610876
A15: Securities lending income | B15: 3 | C15: 250
A16: % lending income | B16: =B15/B8 -> 3.9325843e-05 | C16: =C15/C8 -> 0.00046394486 | D16: =AVERAGE(B16:C16) -> 0.00025163535
A17: Securities on loan | B17: 0.006 | C17: 0.1915
A19: Transaction costs | B19: 187 | C19: 271
A20: % transactie kosten | B20: =B19/B8 -> 0.0024513109 | C20: =C19/C8 -> 0.00050291622 | D20: =AVERAGE(B20:C20) -> 0.0014771135
A22: Derivatives | B22: 0.0003 | C22: 0.0002
A24: Kosten benadering gem verleden | B24: =D7+D13-D16+D20 -> 0.0080865658
A26: Gat met kosten benadering
A28: Schatting kosten toekomst | B28: =D7+C13-C16+C20 -> 0.0062892365
A29: Kosten toekomst zonder lek | B29: =D7-C16+C20 -> 0.0035389714
A31: Gok TD toekomst | B31: =B28-0.05% -> 0.0057892365

Sheet IEMM
A2: iShares MSCI EM UCITS ETF USD (Dist) | J2: Wat valt op
A3: 11-2005 gestart | J3: 2018 transactiekosten staan niet in jaarverslag
B4: 2014 | C4: 2015 | D4: 2016 | E4: 2017 | F4: 2018 | G4: 2019 | H4: Gemiddelde (2015-2019) | J4: TD en kosten match spot on, misschien door niet Acc
A5: Net asset value einde boekjaar | B5: 4734561 | C5: 5047997 | D5: 3166140 | E5: 4715029 | F5: 6294155 | G5: 5078010
A6: Operating expense (TER) | B6: 42886 | C6: 42087 | D6: 30851 | E6: 32797 | F6: 42293 | G6: 40293 | J6: TER nu 0,18%
A7: TER gemeld | B7: 0.0075 | C7: 0.0075 | D7: 0.0075 | E7: 0.0075 | F7: 0.0075 | G7: 0.0075 | H7: =AVERAGE(C7:G7) -> 0.0075
A8: Gemiddeld vermogen | B8: =B6/B7 -> 5718133.3 | C8: =C6/C7 -> 5611600 | D8: =D6/D7 -> 4113466.7 | E8: =E6/E7 -> 4372933.3 | F8: =F6/F7 -> 5639066.7 | G8: =G6/G7 -> 5372400 | J8: Optimized selectie, heeft 1175/1383 posities
A10: Dividend income | B10: 167354 | C10: 163206 | D10: 123158 | E10: 115883 | F10: 144585 | G10: 152689
A11: Taxation | B11: 19009 | C11: 17470 | D11: 13933 | E11: 14701 | F11: 18143 | G11: 21015
A12: Dividend lek | B12: =B11/B10 -> 0.11358557 | C12: =C11/C10 -> 0.10704263 | D12: =D11/D10 -> 0.1131311 | E12: =E11/E10 -> 0.12686071 | F12: =F11/F10 -> 0.12548328 | G12: =G11/G10 -> 0.1376327 | H12: =AVERAGE(C12:G12) -> 0.12203009
A13: % dividend lek | B13: =B11/B8 -> 0.0033243366 | C13: =C11/C8 -> 0.0031131941 | D13: =D11/D8 -> 0.0033871674 | E13: =E11/E8 -> 0.0033618166 | F13: =F11/F8 -> 0.0032173764 | G13: =G11/G8 -> 0.0039116596 | H13: =AVERAGE(C13:G13) -> 0.0033982428
A15: Securities lending income | B15: 2138 | C15: 3036 | D15: 3580 | E15: 3125 | F15: 3040 | G15: 3477
A16: % lending income | B16: =B15/B8 -> 0.00037389824 | C16: =C15/C8 -> 0.00054102217 | D16: =D15/D8 -> 0.00087031215 | E16: =E15/E8 -> 0.00071462329 | F16: =F15/F8 -> 0.0005390963 | G16: =G15/G8 -> 0.00064719678 | H16: =AVERAGE(C16:G16) -> 0.00066245014
A17: Securities on loan | B17: =283768/B5 -> 0.059935441 | C17: =585666/C5 -> 0.11601948 | D17: =485017/D5 -> 0.15318874 | E17: 0.1485 | F17: 0.1747 | G17: 0.1259
A19: Transaction costs | B19: 7297 | C19: 4304 | D19: 2947 | E19: 2419 | G19: 1766
A20: % transactie kosten | B20: =B19/B8 -> 0.0012761157 | C20: =C19/C8 -> 0.00076698268 | D20: =D19/D8 -> 0.00071642734 | E20: =E19/E8 -> 0.0005531756 | F20: =F19/F8 -> 0 | G20: =G19/G8 -> 0.00032871715 | H20: =AVERAGE(C20:G20) -> 0.00047306055
A22: Derivatives | C22: 0.0001 | D22: 0.0001 | E22: 0.0002 | F22: 0.0001 | G22: 0.0005
A24: Kosten benadering verleden | B24: =H7+H13-H16+H20 -> 0.010708853 | C24: 2015-2019
A25: Tracking difference | B25: =TrackingDifference!L32/100 -> 0.01072 | C25: 2015-2019
A26: Gat met kosten benadering | B26: =B25-B24 -> 1.1146771e-05
A28: Schatting kosten toekomst | B28: =0.18%+AVERAGE(B13:G13)+G20-AVERAGE(F16:G16) -> 0.0049214957
A29: Verschil kosten toekomst en verleden | B29: =B28-B24 -> -0.0057873575
A31: Tracking diff toekomst | B31: =B25+B29 -> 0.0049326425

Sheet IEMA
A2: iShares MSCI EM UCITS ETF USD (Acc) | J2: Wat valt op
A3: 09-2009 gestart | J3: Optimized selectie, heeft 902/1383 posities
B4: 2014 | C4: 2015 | D4: 2016 | E4: 2017 | F4: 2018 | G4: 2019 | H4: Gemiddelde (2015-2019)
A5: Net asset value einde boekjaar | B5: 350218 | C5: 324297 | D5: 405793 | E5: 1117955 | F5: 913207 | G5: 736031
A6: Operating expense (TER) | B6: 2308 | C6: 2382 | D6: 2122 | E6: 4064 | F6: 7478 | G6: 4948 | J6: TER nu 0,18%
A7: TER gemeld | B7: 0.007 | C7: 0.0068 | D7: 0.0068 | E7: 0.0068 | F7: 0.0068 | G7: 0.0068 | H7: =AVERAGE(C7:G7) -> 0.0068
A8: Gemiddeld vermogen | B8: =B6/B7 -> 329714.29 | C8: =C6/C7 -> 350294.12 | D8: =D6/D7 -> 312058.82 | E8: =E6/E7 -> 597647.06 | F8: =F6/F7 -> 1099705.9 | G8: =G6/G7 -> 727647.06
A10: Dividend income | B10: 8538 | C10: 10266 | D10: 9688 | E10: 16633 | F10: 28168 | G10: 22036
A11: Taxation | B11: 950 | C11: 1134 | D11: 1113 | E11: 2015 | F11: 4030 | G11: 3336
A12: Dividend lek | B12: =B11/B10 -> 0.11126728 | C12: =C11/C10 -> 0.11046172 | D12: =D11/D10 -> 0.11488439 | E12: =E11/E10 -> 0.12114471 | F12: =F11/F10 -> 0.14307015 | G12: =G11/G10 -> 0.15138864 | H12: =AVERAGE(C12:G12) -> 0.12818992
A13: % dividend lek | B13: =B11/B8 -> 0.0028812825 | C13: =C11/C8 -> 0.0032372796 | D13: =D11/D8 -> 0.0035666352 | E13: =E11/E8 -> 0.0033715551 | F13: =F11/F8 -> 0.0036646162 | G13: =G11/G8 -> 0.0045846403 | H13: =AVERAGE(C13:G13) -> 0.0036849453
A15: Securities lending income | B15: 93 | C15: 172 | D15: 188 | E15: 267 | F15: 495 | G15: 335
A16: % lending income | B16: =B15/B8 -> 0.00028206239 | C16: =C15/C8 -> 0.00049101595 | D16: =D15/D8 -> 0.00060245052 | E16: =E15/E8 -> 0.00044675197 | F16: =F15/F8 -> 0.00045012035 | G16: =G15/G8 -> 0.00046038804 | H16: =AVERAGE(C16:G16) -> 0.00049014537
A17: Securities on loan | B17: =12930/B5 -> 0.036919861 | C17: =28180/C5 -> 0.086895654 | D17: =22862/D5 -> 0.056339069 | E17: 0.1393 | F17: 0.1368 | G17: 0.0686
A19: Transaction costs | B19: 276 | C19: 150 | D19: 318 | E19: 903 | F19: 754 | G19: 686
A20: % transactie kosten | B20: =B19/B8 -> 0.00083708839 | C20: =C19/C8 -> 0.00042821159 | D20: =D19/D8 -> 0.0010190386 | E20: =E19/E8 -> 0.0015109252 | F20: =F19/F8 -> 0.00068563787 | G20: =G19/G8 -> 0.00094276475 | H20: =AVERAGE(C20:G20) -> 0.00091731561
A22: Derivatives | C22: 0 | D22: 0.0002 | E22: 0 | F22: 0.0002 | G22: 0.0002
A24: Kosten benadering verleden | B24: =H7+H13-H16+H20 -> 0.010912116 | C24: 2015-2019
A25: Tracking difference | B25: =TrackingDifference!L39/100 -> 0.01026 | C25: 2015-2019
A26: Gat met kosten benadering | B26: =B25-B24 -> -0.00065211553
A28: Schatting kosten toekomst | B28: =0.18%+AVERAGE(B13:G13)+AVERAGE(F20:G20)-AVERAGE(F16:G16) -> 0.0057099486
A29: Verschil kosten toekomst en verleden | B29: =B28-B24 -> -0.0052021669
A31: Tracking diff toekomst | B31: =B25+B29 -> 0.0050578331

Sheet IWVL
A2: iShares Edge MSCI World Value Factor UCITS ETF | I2: Wat valt op
A3: 10-2014 gestart | I3: Optimized selectie, heeft 395/400 posities
B4: 2015 | C4: 2016 | D4: 2017 | E4: 2018 | F4: 2019 | G4: Gemiddelde (2016-2019) | I4: boekjaar loopt tot eind mei van het jaar
A5: Net asset value einde boekjaar | B5: 24256 | C5: 151277 | D5: 1038524 | E5: 1613172 | F5: 1651193
A6: Operating expense (TER) | B6: 30 | C6: 209 | D6: 1984 | E6: 3734 | F6: 4812 | I6: Transactiekosten 2018 niet te vinden
A7: TER gemeld | B7: 0.003 | C7: 0.003 | D7: 0.003 | E7: 0.003 | F7: 0.003 | G7: =AVERAGE(C7:F7) -> 0.003 | I7: 2015 startjaar?
A8: Gemiddeld vermogen | B8: =B6/B7 -> 10000 | C8: =C6/C7 -> 69666.667 | D8: =D6/D7 -> 661333.33 | E8: =E6/E7 -> 1244666.7 | F8: =F6/F7 -> 1604000 | I8: Lek wat lager, dividend wat hoger
A10: Dividend income | B10: 279 | C10: 2604 | D10: 21736 | E10: 38305 | F10: 56439
A11: Taxation | B11: 29 | C11: 282 | D11: 2230 | E11: 3979 | F11: 5829
A12: Dividend lek | B12: =B11/B10 -> 0.10394265 | C12: =C11/C10 -> 0.10829493 | D12: =D11/D10 -> 0.10259477 | E12: =E11/E10 -> 0.10387678 | F12: =F11/F10 -> 0.10327965 | G12: =AVERAGE(C12:F12) -> 0.10451153
A13: % dividend lek | B13: =B11/B8 -> 0.0029 | C13: =C11/C8 -> 0.0040478469 | D13: =D11/D8 -> 0.0033719758 | E13: =E11/E8 -> 0.0031968399 | F13: =F11/F8 -> 0.0036340399 | G13: =AVERAGE(C13:F13) -> 0.0035626756
A14: % dividend | B14: =B10/B8 -> 0.0279 | C14: =C10/C8 -> 0.03737799 | D14: =D10/D8 -> 0.032866935 | E14: =E10/E8 -> 0.030775308 | F14: =F10/F8 -> 0.035186409 | G14: =AVERAGE(C14:F14) -> 0.034051661
A16: Securities lending income | B16: 1 | C16: 7 | D16: 74 | E16: 195 | F16: 342
A17: % lending income | B17: =B16/B8 -> 0.0001 | C17: =C16/C8 -> 0.00010047847 | D17: =D16/D8 -> 0.00011189516 | E17: =E16/E8 -> 0.00015666845 | F17: =F16/F8 -> 0.00021321696 | G17: =AVERAGE(C17:F17) -> 0.00014556476
A18: Securities on loan | B18: =56/B5 -> 0.0023087071 | D18: 0.0794 | E18: 0.0756 | F18: 0.1271
A20: Transaction costs | B20: 16 | C20: 86 | D20: 866 | F20: 1656
A21: % transactie kosten | B21: =B20/B8 -> 0.0016 | C21: =C20/C8 -> 0.0012344498 | D21: =D20/D8 -> 0.0013094758 | F21: =F20/F8 -> 0.001032419 | G21: =AVERAGE(C21:F21) -> 0.0011921148
A23: Derivatives | B23: 0 | D23: 0.0001 | E23: 0 | F23: 0.0004
A25: Kosten benadering verleden | B25: =G7+G13-G17+G21 -> 0.0076092257 | C25: 2016-2019
A26: Tracking difference | B26: =TrackingDifference!L46/100 -> 0.006625 | C26: 2016-2019
A27: Gat met kosten benadering | B27: =B26-B25 -> -0.00098422569
A29: Schatting kosten toekomst | B29: =F7++G13-F17+F21 -> 0.0073818776
A30: Verschil kosten toekomst en verleden | B30: =B29-B25 -> -0.00022734808
A32: Tracking diff toekomst | B32: =B26+B30 -> 0.0063976519

Sheet TrackingDifference
C1: 2013 | D1: 2014 | E1: 2015 | F1: 2016 | G1: 2017 | H1: 2018 | I1: 2019 | J1: Gem performance | L1: TD | M1: OPNI
B2: iShares IWDA | D2: 5.05 | E2: -0.77 | F2: 7.73 | G2: 22.45 | H2: -8.65 | I2: 27.76 | J2: =AVERAGE(D2:I2) -> 8.9283333
B3: MSCI WORLD INDEX (USD) gross | D3: 5.5 | E3: -0.32 | F3: 8.15 | G3: 23.07 | H3: -8.2 | I3: 28.4
B4: MSCI WORLD INDEX (USD) NET | D4: 4.94 | E4: -0.87 | F4: 7.51 | G4: 22.4 | H4: -8.71 | I4: 27.67
B5: Vs gross | D5: =D3-D2 -> 0.45 | E5: =E3-E2 -> 0.45 | F5: =F3-F2 -> 0.42 | G5: =G3-G2 -> 0.62 | H5: =H3-H2 -> 0.45 | I5: =I3-I2 -> 0.64 | L5: =AVERAGE(D5:I5) -> 0.505
B6: Vs net | D6: =D2-D4 -> 0.11 | E6: =E2-E4 -> 0.1 | F6: =F2-F4 -> 0.22 | G6: =G2-G4 -> 0.05 | H6: =H2-H4 -> 0.06 | I6: =I2-I4 -> 0.09 | M6: =AVERAGE(D6:I6) -> 0.105
B9: iShares EMIM | E9: -14.38 | F9: 9.61 | G9: 36.98 | H9: -14.83 | I9: 17.45 | J9: =AVERAGE(D9:I9) -> 6.966
B10: MSCI EMERGING MARKETS IMI (USD) GROSS | E10: -13.55 | F10: 10.3 | G10: 37.28 | H10: -14.71 | I10: 18.1
B11: MSCI EMERGING MARKETS IMI (USD) NET | E11: -13.86 | F11: 9.9 | G11: 36.83 | H11: -15.04 | I11: 17.64
B12: Vs gross | E12: =E10-E9 -> 0.83 | F12: =F10-F9 -> 0.69 | G12: =G10-G9 -> 0.3 | H12: =H10-H9 -> 0.12 | I12: =I10-I9 -> 0.65 | L12: =AVERAGE(E12:I12) -> 0.518
B13: Vs net | E13: =E9-E11 -> -0.52 | F13: =F9-F11 -> -0.29 | G13: =G9-G11 -> 0.15 | H13: =H9-H11 -> 0.21 | I13: =I9-I11 -> -0.19 | M13: =AVERAGE(E13:I13) -> -0.128
B16: iShares IUSN | I16: 25.73
B17: Bruto index | I17: 26.78
B18: Netto index | I18: 26.19
B19: Vs gross | I19: =I17-I16 -> 1.05 | L19: =AVERAGE(I19) -> 1.05 | N19: optimized selectie zit er naast
B22: iShares IEMS | E22: -7.43 | F22: 2.31 | G22: 33.89 | H22: -18.63 | I22: 11.06 | J22: =AVERAGE(D22:I22) -> 4.24
B23: Bruto index | E23: -6.85 | F23: 2.28 | G23: 33.84 | H23: -18.59 | I23: 11.5
B24: Netto index | E24: -6.57 | F24: 2.56 | G24: 34.22 | H24: -18.3 | I24: 11.92
B25: Vs gross | E25: =E24-E22 -> 0.86 | F25: =F24-F22 -> 0.25 | G25: =G24-G22 -> 0.33 | H25: =H24-H22 -> 0.33 | I25: =I24-I22 -> 0.86 | L25: =AVERAGE(E25:I25) -> 0.526
B26: Vs net | E26: =E22-E23 -> -0.58 | F26: =F22-F23 -> 0.03 | G26: =G22-G23 -> 0.05 | H26: =H22-H23 -> -0.04 | I26: =I22-I23 -> -0.44 | M26: =AVERAGE(E26:I26) -> -0.196
B29: iShares IEMM | E29: -15.34 | F29: 10.52 | G29: 36.47 | H29: -15.09 | I29: 17.47 | J29: =AVERAGE(E29:I29) -> 6.806
B30: Bruto index | E30: -14.92 | F30: 11.19 | G30: 37.28 | H30: -14.57 | I30: 18.42
B31: Netto index | E31: -14.6 | F31: 11.6 | G31: 37.75 | H31: -14.24 | I31: 18.88
B32: Vs gross | E32: =E31-E29 -> 0.74 | F32: =F31-F29 -> 1.08 | G32: =G31-G29 -> 1.28 | H32: =H31-H29 -> 0.85 | I32: =I31-I29 -> 1.41 | L32: =AVERAGE(E32:I32) -> 1.072
B33: Vs net | E33: =E29-E30 -> -0.42 | F33: =F29-F30 -> -0.67 | G33: =G29-G30 -> -0.81 | H33: =H29-H30 -> -0.52 | I33: =I29-I30 -> -0.95 | M33: =AVERAGE(E33:I33) -> -0.674
B36: iShares IEMA | E36: -15.33 | F36: 10.57 | G36: 36.59 | H36: -15.11 | I36: 17.54
B37: Bruto index | E37: -14.6 | F37: 11.6 | G37: 37.75 | H37: -14.24 | I37: 18.88
B38: Netto index | E38: -14.92 | F38: 11.19 | G38: 37.28 | H38: -14.57 | I38: 18.42
B39: Vs gross | E39: =E37-E36 -> 0.73 | F39: =F37-F36 -> 1.03 | G39: =G37-G36 -> 1.16 | H39: =H37-H36 -> 0.87 | I39: =I37-I36 -> 1.34 | L39: =AVERAGE(E39:I39) -> 1.026
B40: Vs net | E40: =E36-E38 -> -0.41 | F40: =F36-F38 -> -0.62 | G40: =G36-G38 -> -0.69 | H40: =H36-H38 -> -0.54 | I40: =I36-I38 -> -0.88 | M40: =AVERAGE(E40:I40) -> -0.628
B43: iShares IWVL | E43: -3.27 | F43: 8.14 | G43: 22.16 | H43: -13.9 | I43: 19.13
B44: MSCI World Enhanced Value Index (USD) gross | E44: -2.73 | F44: 8.86 | G44: 22.88 | H44: -13.4 | I44: 19.84
B45: MSCI World Enhanced Value Index (USD) NET | E45: -3.28 | F45: 8.13 | G45: 22.15 | H45: -13.93 | I45: 18.99
B46: Vs gross | E46: =E44-E43 -> 0.54 | F46: =F44-F43 -> 0.72 | G46: =G44-G43 -> 0.72 | H46: =H44-H43 -> 0.5 | I46: =I44-I43 -> 0.71 | L46: =AVERAGE(F46:I46) -> 0.6625
B47: Vs net | E47: =E45-E43 -> -0.01 | F47: =F45-F43 -> -0.01 | G47: =G45-G43 -> -0.01 | H47: =H45-H43 -> -0.03 | I47: =I45-I43 -> -0.14 | M47: =SUM(F47:I47) -> -0.19
